backlog_puller/__init__.py
backlog_puller/__main__.py
backlog_puller-1.0.0.dist-info/DESCRIPTION.rst
backlog_puller-1.0.0.dist-info/METADATA
backlog_puller-1.0.0.dist-info/RECORD
backlog_puller-1.0.0.dist-info/WHEEL
backlog_puller-1.0.0.dist-info/entry_points.txt
backlog_puller-1.0.0.dist-info/metadata.json
backlog_puller-1.0.0.dist-info/top_level.txt
