Metadata-Version: 2.0
Name: backlog-puller
Version: 1.0.0
Summary: A python module for pulling data from a backloggery account in a variety of different formats
Home-page: https://github.com/GTmmiller/backlog_puller
Author: Steven Miller
Author-email: msm@gatech.edu
License: MIT
Keywords: video games backlog puller
Platform: UNKNOWN
Classifier: Development Status :: 4 - Beta
Classifier: Intended Audience :: Developers
Classifier: License :: OSI Approved :: MIT License
Classifier: Operating System :: OS Independent
Classifier: Programming Language :: Python :: 2.6
Classifier: Programming Language :: Python :: 2.7
Classifier: Programming Language :: Python :: 2 :: Only
Classifier: Topic :: Games/Entertainment
Classifier: Topic :: Internet
